[
  {
    "lat": 44.85915,
    "lng": 13.81848,
    "time": 1754241692
  },
  {
    "lat": 44.85917,
    "lng": 13.81855,
    "time": 1754241754
  },
  {
    "lat": 44.85919,
    "lng": 13.81854,
    "time": 1754241815
  },
  {
    "lat": 44.85922,
    "lng": 13.81844,
    "time": 1754241876
  },
  {
    "lat": 44.85922,
    "lng": 13.8184,
    "time": 1754241937
  },
  {
    "lat": 44.8591,
    "lng": 13.8186,
    "time": 1754247507
  },
  {
    "lat": 44.85298,
    "lng": 13.81929,
    "time": 1754386210
  },
  {
    "lat": 44.84996,
    "lng": 13.81941,
    "time": 1754386309
  },
  {
    "lat": 40.92015,
    "lng": 17.50622,
    "time": 1751458515
  },
  {
    "lat": 44.84813,
    "lng": 13.81978,
    "time": 1754386369
  },
  {
    "lat": 44.84632,
    "lng": 13.82015,
    "time": 1754386430
  },
  {
    "lat": 44.84446,
    "lng": 13.82053,
    "time": 1754386491
  },
  {
    "lat": 44.8426,
    "lng": 13.82105,
    "time": 1754386552
  },
  {
    "lat": 44.84078,
    "lng": 13.82183,
    "time": 1754386613
  },
  {
    "lat": 44.83897,
    "lng": 13.82255,
    "time": 1754386673
  },
  {
    "lat": 44.83716,
    "lng": 13.82323,
    "time": 1754386734
  },
  {
    "lat": 44.8354,
    "lng": 13.82405,
    "time": 1754386795
  },
  {
    "lat": 44.83395,
    "lng": 13.82556,
    "time": 1754386856
  },
  {
    "lat": 44.83289,
    "lng": 13.82764,
    "time": 1754386916
  },
  {
    "lat": 44.83207,
    "lng": 13.82984,
    "time": 1754386977
  },
  {
    "lat": 44.83162,
    "lng": 13.83216,
    "time": 1754387038
  },
  {
    "lat": 44.83203,
    "lng": 13.83446,
    "time": 1754387099
  },
  {
    "lat": 44.83253,
    "lng": 13.83675,
    "time": 1754387160
  },
  {
    "lat": 44.83324,
    "lng": 13.83895,
    "time": 1754387220
  },
  {
    "lat": 44.83417,
    "lng": 13.84098,
    "time": 1754387281
  },
  {
    "lat": 44.83561,
    "lng": 13.84224,
    "time": 1754387342
  },
  {
    "lat": 44.83732,
    "lng": 13.8424,
    "time": 1754387403
  },
  {
    "lat": 44.83876,
    "lng": 13.84101,
    "time": 1754387463
  },
  {
    "lat": 44.8387,
    "lng": 13.83954,
    "time": 1754387524
  },
  {
    "lat": 44.83838,
    "lng": 13.83842,
    "time": 1754387585
  },
  {
    "lat": 44.83853,
    "lng": 13.83757,
    "time": 1754387646
  },
  {
    "lat": 44.83865,
    "lng": 13.83724,
    "time": 1754387707
  },
  {
    "lat": 44.83864,
    "lng": 13.83717,
    "time": 1754387767
  },
  {
    "lat": 44.8387,
    "lng": 13.83719,
    "time": 1754387828
  },
  {
    "lat": 44.83858,
    "lng": 13.837,
    "time": 1754387889
  },
  {
    "lat": 44.83874,
    "lng": 13.8369,
    "time": 1754387950
  },
  {
    "lat": 44.83861,
    "lng": 13.83675,
    "time": 1754388011
  },
  {
    "lat": 44.83862,
    "lng": 13.83672,
    "time": 1754388073
  },
  {
    "lat": 44.83862,
    "lng": 13.83672,
    "time": 1754388136
  },
  {
    "lat": 44.83862,
    "lng": 13.83671,
    "time": 1754388199
  },
  {
    "lat": 44.83862,
    "lng": 13.83671,
    "time": 1754388260
  },
  {
    "lat": 44.83863,
    "lng": 13.8367,
    "time": 1754388321
  },
  {
    "lat": 44.83863,
    "lng": 13.83671,
    "time": 1754388382
  },
  {
    "lat": 44.83861,
    "lng": 13.8367,
    "time": 1754388443
  },
  {
    "lat": 44.83862,
    "lng": 13.8367,
    "time": 1754388504
  },
  {
    "lat": 44.83862,
    "lng": 13.83671,
    "time": 1754388564
  },
  {
    "lat": 44.83863,
    "lng": 13.83672,
    "time": 1754388625
  },
  {
    "lat": 44.83863,
    "lng": 13.83673,
    "time": 1754388685
  },
  {
    "lat": 44.83861,
    "lng": 13.83668,
    "time": 1754388746
  },
  {
    "lat": 44.83861,
    "lng": 13.8367,
    "time": 1754388807
  },
  {
    "lat": 44.83861,
    "lng": 13.8367,
    "time": 1754388868
  },
  {
    "lat": 44.83862,
    "lng": 13.8367,
    "time": 1754388929
  },
  {
    "lat": 44.83861,
    "lng": 13.83671,
    "time": 1754388992
  },
  {
    "lat": 44.83862,
    "lng": 13.83671,
    "time": 1754389055
  },
  {
    "lat": 44.83862,
    "lng": 13.83671,
    "time": 1754389115
  },
  {
    "lat": 44.83861,
    "lng": 13.83671,
    "time": 1754389176
  },
  {
    "lat": 44.83855,
    "lng": 13.83738,
    "time": 1754389237
  },
  {
    "lat": 44.83826,
    "lng": 13.83849,
    "time": 1754389298
  },
  {
    "lat": 44.83792,
    "lng": 13.84037,
    "time": 1754389359
  },
  {
    "lat": 44.83719,
    "lng": 13.84192,
    "time": 1754389420
  },
  {
    "lat": 44.83578,
    "lng": 13.8422,
    "time": 1754389480
  },
  {
    "lat": 44.83447,
    "lng": 13.84144,
    "time": 1754389541
  },
  {
    "lat": 44.83326,
    "lng": 13.84049,
    "time": 1754389602
  },
  {
    "lat": 44.83223,
    "lng": 13.83931,
    "time": 1754389663
  },
  {
    "lat": 44.83144,
    "lng": 13.83785,
    "time": 1754389724
  },
  {
    "lat": 44.83085,
    "lng": 13.83671,
    "time": 1754389784
  },
  {
    "lat": 44.83113,
    "lng": 13.83585,
    "time": 1754389845
  },
  {
    "lat": 44.8313,
    "lng": 13.83502,
    "time": 1754389906
  },
  {
    "lat": 44.83031,
    "lng": 13.83422,
    "time": 1754389967
  },
  {
    "lat": 44.82907,
    "lng": 13.83454,
    "time": 1754390028
  },
  {
    "lat": 44.82794,
    "lng": 13.83521,
    "time": 1754390088
  },
  {
    "lat": 44.82668,
    "lng": 13.83587,
    "time": 1754390149
  },
  {
    "lat": 44.82505,
    "lng": 13.83699,
    "time": 1754390210
  },
  {
    "lat": 44.82355,
    "lng": 13.83819,
    "time": 1754390271
  },
  {
    "lat": 44.82205,
    "lng": 13.83943,
    "time": 1754390332
  },
  {
    "lat": 44.82068,
    "lng": 13.84075,
    "time": 1754390392
  },
  {
    "lat": 44.81946,
    "lng": 13.84199,
    "time": 1754390453
  },
  {
    "lat": 44.81827,
    "lng": 13.8432,
    "time": 1754390513
  },
  {
    "lat": 44.81714,
    "lng": 13.84433,
    "time": 1754390575
  },
  {
    "lat": 44.81608,
    "lng": 13.84537,
    "time": 1754390635
  },
  {
    "lat": 44.81508,
    "lng": 13.84633,
    "time": 1754390696
  },
  {
    "lat": 44.81409,
    "lng": 13.84725,
    "time": 1754390757
  },
  {
    "lat": 44.81311,
    "lng": 13.84816,
    "time": 1754390818
  },
  {
    "lat": 44.81179,
    "lng": 13.84942,
    "time": 1754390878
  },
  {
    "lat": 44.81025,
    "lng": 13.85088,
    "time": 1754390939
  },
  {
    "lat": 44.80875,
    "lng": 13.85249,
    "time": 1754391000
  },
  {
    "lat": 44.80725,
    "lng": 13.85407,
    "time": 1754391061
  },
  {
    "lat": 44.80572,
    "lng": 13.8557,
    "time": 1754391122
  },
  {
    "lat": 44.80426,
    "lng": 13.85738,
    "time": 1754391182
  },
  {
    "lat": 44.80276,
    "lng": 13.85901,
    "time": 1754391243
  },
  {
    "lat": 44.80126,
    "lng": 13.86061,
    "time": 1754391304
  },
  {
    "lat": 44.79974,
    "lng": 13.86215,
    "time": 1754391365
  },
  {
    "lat": 44.7982,
    "lng": 13.8637,
    "time": 1754391426
  },
  {
    "lat": 44.79671,
    "lng": 13.86524,
    "time": 1754391487
  },
  {
    "lat": 44.79521,
    "lng": 13.86678,
    "time": 1754391547
  },
  {
    "lat": 44.79369,
    "lng": 13.86835,
    "time": 1754391608
  },
  {
    "lat": 44.79221,
    "lng": 13.86988,
    "time": 1754391669
  },
  {
    "lat": 44.79065,
    "lng": 13.87144,
    "time": 1754391730
  },
  {
    "lat": 44.78911,
    "lng": 13.87298,
    "time": 1754391791
  },
  {
    "lat": 44.78754,
    "lng": 13.87454,
    "time": 1754391852
  },
  {
    "lat": 44.78596,
    "lng": 13.87614,
    "time": 1754391912
  },
  {
    "lat": 44.78438,
    "lng": 13.87769,
    "time": 1754391973
  },
  {
    "lat": 44.78276,
    "lng": 13.87921,
    "time": 1754392034
  },
  {
    "lat": 44.78115,
    "lng": 13.88075,
    "time": 1754392095
  },
  {
    "lat": 44.77962,
    "lng": 13.88241,
    "time": 1754392156
  },
  {
    "lat": 44.7781,
    "lng": 13.88407,
    "time": 1754392216
  },
  {
    "lat": 44.77659,
    "lng": 13.88571,
    "time": 1754392277
  },
  {
    "lat": 44.77503,
    "lng": 13.88738,
    "time": 1754392338
  },
  {
    "lat": 44.77348,
    "lng": 13.88904,
    "time": 1754392399
  },
  {
    "lat": 44.77193,
    "lng": 13.89069,
    "time": 1754392460
  },
  {
    "lat": 44.7703,
    "lng": 13.89238,
    "time": 1754392520
  },
  {
    "lat": 44.76856,
    "lng": 13.89389,
    "time": 1754392581
  },
  {
    "lat": 44.76687,
    "lng": 13.89565,
    "time": 1754392642
  },
  {
    "lat": 44.7652,
    "lng": 13.89751,
    "time": 1754392703
  },
  {
    "lat": 44.76378,
    "lng": 13.89952,
    "time": 1754392764
  },
  {
    "lat": 44.76292,
    "lng": 13.90184,
    "time": 1754392825
  },
  {
    "lat": 44.76243,
    "lng": 13.9043,
    "time": 1754392885
  },
  {
    "lat": 44.76201,
    "lng": 13.90673,
    "time": 1754392945
  },
  {
    "lat": 44.76166,
    "lng": 13.90918,
    "time": 1754393006
  },
  {
    "lat": 44.76119,
    "lng": 13.91173,
    "time": 1754393067
  },
  {
    "lat": 44.76069,
    "lng": 13.9143,
    "time": 1754393128
  },
  {
    "lat": 44.7602,
    "lng": 13.91685,
    "time": 1754393189
  },
  {
    "lat": 44.75968,
    "lng": 13.91941,
    "time": 1754393249
  },
  {
    "lat": 44.75926,
    "lng": 13.92194,
    "time": 1754393311
  },
  {
    "lat": 44.75883,
    "lng": 13.92443,
    "time": 1754393372
  },
  {
    "lat": 44.75838,
    "lng": 13.9269,
    "time": 1754393433
  },
  {
    "lat": 44.75795,
    "lng": 13.92934,
    "time": 1754393493
  },
  {
    "lat": 44.75753,
    "lng": 13.93177,
    "time": 1754393553
  },
  {
    "lat": 44.75709,
    "lng": 13.93417,
    "time": 1754393613
  }
]